pyGrained/__init__.py
pyGrained/utils/SASA.py
pyGrained/utils/__init__.py
pyGrained/utils/atomList.py
pyGrained/utils/bonds.py
pyGrained/utils/coarseGrained.py
pyGrained/utils/geometric.py
pyGrained/utils/nativeContacts.py
pyGrained/utils/output.py
pyGrained/utils/sequence.py
pyGrained/utils/trajectory.py
pyGrained/utils/computeK/__init__.py
pyGrained-1.0.0.dist-info/LICENSE
pyGrained-1.0.0.dist-info/METADATA
pyGrained-1.0.0.dist-info/WHEEL
pyGrained-1.0.0.dist-info/top_level.txt
pyGrained-1.0.0.dist-info/RECORD
