Metadata-Version: 2.1
Name: pyGrained
Version: 1.0.0
Summary: Coarse grained library for Python
Home-page: https://github.com/PabloIbannez/pyGrained
Author-email: Pablo Ibáñez-Freire <p.ibanez.fre@gmail.com>
License: MIT License
Classifier: Development Status :: 3 - Alpha
Classifier: License :: OSI Approved :: MIT License
Classifier: Programming Language :: Python :: 3
Classifier: Programming Language :: Python :: 3.6
Classifier: Programming Language :: Python :: 3.7
Classifier: Programming Language :: Python :: 3.8
Classifier: Programming Language :: Python :: 3.9
Requires-Python: >=3.7
License-File: LICENSE
Requires-Dist: pathlib
Requires-Dist: uuid
Requires-Dist: numpy
Requires-Dist: scipy
